flask_dbmigrant/__init__.py
flask_dbmigrant-1.0.3.dist-info/LICENSE
flask_dbmigrant-1.0.3.dist-info/METADATA
flask_dbmigrant-1.0.3.dist-info/WHEEL
flask_dbmigrant-1.0.3.dist-info/RECORD
