Metadata-Version: 2.1
Name: flask-dbmigrant
Version: 1.0.3
Summary: Flask extension for working with Alembic
Author: Rafal Padkowski
Author-email: rafaelp@poczta.onet.pl
Requires-Python: >=3.10
Classifier: Programming Language :: Python :: 3
Classifier: Programming Language :: Python :: 3.10
Classifier: Programming Language :: Python :: 3.11
Classifier: Programming Language :: Python :: 3.12
Requires-Dist: alembic (>=1.13.1)
Requires-Dist: flask (>=3.0.2)
